Time_Series_Scalogram/__init__.py
Time_Series_Scalogram/hampel_filter.py
Time_Series_Scalogram/ts_scalogram.py
time_series_scalogram-0.0.4.dist-info/METADATA
time_series_scalogram-0.0.4.dist-info/WHEEL
time_series_scalogram-0.0.4.dist-info/licenses/LICENSE
time_series_scalogram-0.0.4.dist-info/RECORD
