Metadata-Version: 2.3
Name: Time_Series_Scalogram
Version: 0.0.4
Summary: Calculate and visualize a scalogram from any time series
Project-URL: Homepage, https://github.com/huangzesen/Time-Series-Scalogram-Public
Project-URL: Issues, https://github.com/huangzesen/Time-Series-Scalogram-Public/issues
Author-email: Zesen Huang <huangzs1997@gmail.com>
License-File: LICENSE
Classifier: License :: OSI Approved :: MIT License
Classifier: Operating System :: OS Independent
Classifier: Programming Language :: Python :: 3
Requires-Python: >=3.10
Requires-Dist: matplotlib
Requires-Dist: numba
Requires-Dist: numpy
Requires-Dist: pandas
Requires-Dist: scipy
Requires-Dist: tqdm
